Metadata-Version: 2.1
Name: re_copilot
Version: 0.0.1
Summary: Microsoft's Bing Chat AI
Author-email: JE-Chen <jechenmailman@gmail.com>
License: MIT
Project-URL: Homepage, https://github.com/Integration-Automation/ReCopilot
Project-URL: Code, https://github.com/Integration-Automation/ReCopilot
Classifier: Programming Language :: Python :: 3.9
Classifier: Development Status :: 2 - Pre-Alpha
Classifier: Environment :: Win32 (MS Windows)
Classifier: Environment :: MacOS X
Classifier: Environment :: X11 Applications
Classifier: License :: OSI Approved :: MIT License
Classifier: Operating System :: OS Independent
Requires-Python: >=3.9
License-File: LICENSE
Requires-Dist: aiohttp
Requires-Dist: requests
Requires-Dist: httpx
